Metadata-Version: 2.1
Name: SBstoat
Version: 1.141
Summary: Parameter fitting for SBML models
Home-page: http://tellurium.analogmachine.org
Author: H M Sauro, J Hellerstein
Author-email: hsauro@uw.edu
License: MIT
Platform: UNKNOWN
Classifier: License :: OSI Approved :: MIT License
Classifier: Programming Language :: Python :: 3.6
Classifier: Programming Language :: Python :: 3.7
Classifier: Operating System :: OS Independent
Requires-Python: >=3.6
